jinxif/__init__.py
jinxif/_version.py
jinxif/afsub.py
jinxif/basic.py
jinxif/codex.py
jinxif/config.py
jinxif/configure.py
jinxif/feat.py
jinxif/imgmeta.py
jinxif/jfplt.py
jinxif/keypointregist.py
jinxif/mics.py
jinxif/ometiff.py
jinxif/regist.py
jinxif/sane.py
jinxif/segment.py
jinxif/stitch.py
jinxif/thresh.py
jinxif/util.py
jinxif/src/template_afsubtraction_slidepxscene.py
jinxif/src/template_crop_mscene.py
jinxif/src/template_exposuretimecorrect_slidepxscene.py
jinxif/src/template_extractfeatures_slide.py
jinxif/src/template_featurecorrectlabels_slide.py
jinxif/src/template_filterfeatures_slide.py
jinxif/src/template_micspatch_slide.py
jinxif/src/template_micstrafo_batch.py
jinxif/src/template_nuccellzprojlabel_slide.py
jinxif/src/template_ometiff_slidepxscene.py
jinxif/src/template_registration_mscene.m
jinxif/src/template_registration_mscene.py
jinxif/src/template_segmentation_match.py
jinxif/src/template_segmentation_nuccell.py
jinxif/src/template_thresh_slide.py
jinxif/src/template_vizrawimage_slide.py
jinxif/src/template_vizregimage_slide.py
jinxif/src/template_xzcompress_slide.py
jinxif/src/template_xzdecompress_slide.py
jinxif-0.0.49.dist-info/LICENSE
jinxif-0.0.49.dist-info/METADATA
jinxif-0.0.49.dist-info/WHEEL
jinxif-0.0.49.dist-info/top_level.txt
jinxif-0.0.49.dist-info/RECORD
