Metadata-Version: 2.1
Name: jinxif
Version: 0.0.49
Summary: A python3-based image analysis package to achieve fully-documented and reproducible visualization and analysis of bio-medical microscopy images. This is a fork from Jennifer Eng`s mplex_image software library.
Home-page: https://gitlab.com/bue/jinxif
Author: Elmar Bucher
Author-email: ulmusfagus@tutanota.de
License: GPL>=3
Project-URL: Bug Reports, https://gitlab.com/bue/jinxif/-/issues
Project-URL: Say Thanks!, https://donate.doctorswithoutborders.org
Project-URL: Source, https://gitlab.com/bue/jinxif
Keywords: multiplex imaging,cyclic immunofluorescence,image processing,image data extraction,image analysis
Platform: UNKNOWN
Classifier: Development Status :: 5 - Production/Stable
Classifier: Intended Audience :: Developers
Classifier: Intended Audience :: Science/Research
Classifier: Topic :: Scientific/Engineering :: Bio-Informatics
Classifier: License :: OSI Approved :: GNU General Public License v3 or later (GPLv3+)
Classifier: Programming Language :: Python :: 3.6
Requires-Python: >=3.6,<3.9
License-File: LICENSE
Requires-Dist: aicsimageio
Requires-Dist: cellpose
Requires-Dist: imagecodecs
Requires-Dist: matplotlib
Requires-Dist: numpy
Requires-Dist: numba
Requires-Dist: ome-types
Requires-Dist: opencv-python
Requires-Dist: pandas
Requires-Dist: pillow
Requires-Dist: scikit-image
Requires-Dist: scipy
Requires-Dist: seaborn
Requires-Dist: torch
